qgweb3/__init__.py
qgweb3/cui_qiu_client.py
qgweb3/date_util.py
qgweb3/galxe.py
qgweb3/ip_util.py
qgweb3/logging_utils.py
qgweb3/qg_eth.py
qgweb3/qg_util.py
qgweb3/random_util.py
qgweb3-1.0.3.dist-info/LICENSE
qgweb3-1.0.3.dist-info/METADATA
qgweb3-1.0.3.dist-info/WHEEL
qgweb3-1.0.3.dist-info/top_level.txt
qgweb3-1.0.3.dist-info/RECORD
